{
  "id": "760444",
  "day": "2026-06-20",
  "kickoffISO": "2026-06-20T00:30Z",
  "round": "group",
  "group": "C",
  "home": {
    "abbr": "BRA",
    "name": "Brazil",
    "colorHex": "#fee000",
    "score": 3
  },
  "away": {
    "abbr": "HAI",
    "name": "Haiti",
    "colorHex": "#0033a0",
    "score": 0
  },
  "fingerprint": {
    "momentumSeries": [
      {
        "t": 0,
        "v": 0
      },
      {
        "t": 1,
        "v": 0
      },
      {
        "t": 2,
        "v": -0.2167
      },
      {
        "t": 3,
        "v": -0.1831
      },
      {
        "t": 4,
        "v": 0.2312
      },
      {
        "t": 5,
        "v": 0.1955
      },
      {
        "t": 6,
        "v": 0.3641
      },
      {
        "t": 7,
        "v": 0.3104
      },
      {
        "t": 8,
        "v": 0.2635
      },
      {
        "t": 9,
        "v": 0.0118
      },
      {
        "t": 10,
        "v": 0.0099
      },
      {
        "t": 11,
        "v": 0.2514
      },
      {
        "t": 12,
        "v": 0.3185
      },
      {
        "t": 13,
        "v": 0.3775
      },
      {
        "t": 14,
        "v": 0.0874
      },
      {
        "t": 15,
        "v": 0.0735
      },
      {
        "t": 16,
        "v": 0.0618
      },
      {
        "t": 17,
        "v": 0.7045
      },
      {
        "t": 18,
        "v": 0.6272
      },
      {
        "t": 19,
        "v": 0.4652
      },
      {
        "t": 20,
        "v": 0.4001
      },
      {
        "t": 21,
        "v": 0.535
      },
      {
        "t": 22,
        "v": 0.5493
      },
      {
        "t": 23,
        "v": 0.9813
      },
      {
        "t": 24,
        "v": 0.9612
      },
      {
        "t": 25,
        "v": 0.9287
      },
      {
        "t": 26,
        "v": 0.8824
      },
      {
        "t": 27,
        "v": 0.823
      },
      {
        "t": 28,
        "v": 0.7533
      },
      {
        "t": 29,
        "v": 0.8902
      },
      {
        "t": 30,
        "v": 0.8326
      },
      {
        "t": 31,
        "v": 0.7049
      },
      {
        "t": 32,
        "v": 0.6276
      },
      {
        "t": 33,
        "v": 0.5512
      },
      {
        "t": 34,
        "v": 0.2817
      },
      {
        "t": 35,
        "v": 0.2388
      },
      {
        "t": 36,
        "v": 0.8805
      },
      {
        "t": 37,
        "v": 0.8206
      },
      {
        "t": 38,
        "v": 0.6971
      },
      {
        "t": 39,
        "v": 0.7348
      },
      {
        "t": 40,
        "v": 0.6582
      },
      {
        "t": 41,
        "v": 0.4082
      },
      {
        "t": 42,
        "v": 0.3491
      },
      {
        "t": 43,
        "v": 0.2972
      },
      {
        "t": 44,
        "v": 0.2522
      },
      {
        "t": 45,
        "v": 0.9103
      },
      {
        "t": 46,
        "v": 0.8581
      },
      {
        "t": 47,
        "v": 0.7937
      },
      {
        "t": 48,
        "v": 0.7208
      },
      {
        "t": 49,
        "v": 0.5118
      },
      {
        "t": 50,
        "v": 0.4424
      },
      {
        "t": 51,
        "v": 0.3797
      },
      {
        "t": 52,
        "v": 0.324
      },
      {
        "t": 53,
        "v": 0.052
      },
      {
        "t": 54,
        "v": 0.0437
      },
      {
        "t": 55,
        "v": 0.0368
      },
      {
        "t": 56,
        "v": 0.0309
      },
      {
        "t": 57,
        "v": 0.026
      },
      {
        "t": 58,
        "v": 0.0219
      },
      {
        "t": 59,
        "v": 0.1262
      },
      {
        "t": 60,
        "v": 0.1063
      },
      {
        "t": 61,
        "v": -0.1445
      },
      {
        "t": 62,
        "v": -0.3408
      },
      {
        "t": 63,
        "v": -0.7022
      },
      {
        "t": 64,
        "v": -0.6249
      },
      {
        "t": 65,
        "v": -0.7139
      },
      {
        "t": 66,
        "v": -0.889
      },
      {
        "t": 67,
        "v": -0.8311
      },
      {
        "t": 68,
        "v": -0.7067
      },
      {
        "t": 69,
        "v": -0.6294
      },
      {
        "t": 70,
        "v": -0.553
      },
      {
        "t": 71,
        "v": -0.4804
      },
      {
        "t": 72,
        "v": -0.1497
      },
      {
        "t": 73,
        "v": -0.3594
      },
      {
        "t": 74,
        "v": -0.5048
      },
      {
        "t": 75,
        "v": -0.2167
      },
      {
        "t": 76,
        "v": 0.1763
      },
      {
        "t": 77,
        "v": 0.3613
      },
      {
        "t": 78,
        "v": 0.4049
      },
      {
        "t": 79,
        "v": 0.5279
      },
      {
        "t": 80,
        "v": 0.4572
      },
      {
        "t": 81,
        "v": 0.3929
      },
      {
        "t": 82,
        "v": 0.1167
      },
      {
        "t": 83,
        "v": 0.0983
      },
      {
        "t": 84,
        "v": 0.3147
      },
      {
        "t": 85,
        "v": 0.2673
      },
      {
        "t": 86,
        "v": 0.4187
      },
      {
        "t": 87,
        "v": -0.2588
      },
      {
        "t": 88,
        "v": -0.2191
      },
      {
        "t": 89,
        "v": -0.4649
      },
      {
        "t": 90,
        "v": -0.8202
      },
      {
        "t": 91,
        "v": -0.7502
      }
    ],
    "goals": [
      {
        "t": 23,
        "team": "home",
        "scorer": "Matheus Cunha"
      },
      {
        "t": 36,
        "team": "home",
        "scorer": "Matheus Cunha"
      },
      {
        "t": 45,
        "team": "home",
        "scorer": "Vinícius Júnior"
      }
    ],
    "reds": [],
    "yellows": [
      {
        "t": 3,
        "team": "away"
      },
      {
        "t": 45,
        "team": "away"
      },
      {
        "t": 64,
        "team": "home"
      },
      {
        "t": 72,
        "team": "away"
      }
    ],
    "penalties": [],
    "finalMomentum": -0.7502,
    "possessionHome": 56.7,
    "possessionAway": 43.3,
    "shotsHome": 8,
    "shotsAway": 7,
    "sotHome": 5,
    "sotAway": 3,
    "cornersHome": 4,
    "cornersAway": 4
  }
}